<?xml version="1.0" encoding="UTF-8"?>

<databaseChangeLog xmlns="http://www.liquibase.org/xml/ns/dbchangelog/1.9"
    xmlns:xsi="http://www.w3.org/2001/XMLSchema-instance"
    xsi:schemaLocation="http://www.liquibase.org/xml/ns/dbchangelog/1.9
         http://www.liquibase.org/xml/ns/dbchangelog/dbchangelog-1.9.xsd"
    logicalFilePath="de/communardo/kenmei/database/update/v1.1.3/db.changelog.v1.1.3.xml">
    
    <changeSet id="mt3329_1_postgresql" author="unknown" context="client" dbms="postgresql">
        <comment>CR 96 - support for hierarchical groups: add user_of_group and copy users</comment>
        <createTable tableName="user_of_group">
            <column name="ID" type="BIGINT"><constraints nullable="false" primaryKey="true"/></column>
            <column name="MODIFICATION_TYPE" type="varchar(1024)"><constraints nullable="true" /></column>
            <column name="GROUP_FK" type="BIGINT"><constraints nullable="false" /></column>
            <column name="USER_FK" type="BIGINT"><constraints nullable="false" /></column>
        </createTable>
        
        <createSequence sequenceName="user_of_group_seq"/>
        
        <sql>
            INSERT INTO user_of_group (ID,MODIFICATION_TYPE,GROUP_FK,USER_FK) (SELECT nextval('user_of_group_seq'), null, groups_fk, group_members_fk FROM user_group_member m inner join user_user u on u.ID=m.group_members_fk);
        </sql>
        
        <addForeignKeyConstraint constraintName="user_of_group_group_fkc" baseTableName="user_of_group" baseColumnNames="GROUP_FK" referencedTableName="user_group" referencedColumnNames="ID"/>
        <addForeignKeyConstraint constraintName="user_of_group_user_fkc" baseTableName="user_of_group" baseColumnNames="USER_FK" referencedTableName="user_user" referencedColumnNames="ID"/>
    </changeSet>
    
</databaseChangeLog>